<!DOCTYPE codename-engine-character>
<character x="100" icon="pico" camx="-100" y="300" isGF="false" color="#B7D855" flipX="true" isPlayer="true" gameOverChar="picodead" sprite="pico_house">
	<anim x="0" loop="false" y="0" fps="24" anim="Pico Idle Dance" name="idle"/>
	<anim x="-49" loop="false" y="2" fps="24" anim="Pico Note Right0" name="singLEFT"/>
	<anim x="97" loop="false" y="-81" fps="24" anim="Pico Down Note0" name="singDOWN"/>
	<anim x="6" loop="false" y="26" fps="24" anim="pico Up note0" name="singUP"/>
	<anim x="84" loop="false" y="-11" fps="24" anim="Pico NOTE LEFT0" name="singRIGHT"/>
	<anim x="-42" loop="false" y="49" fps="24" anim="Pico Note Right Miss" name="singLEFTmiss"/>
	<anim x="88" loop="false" y="-39" fps="24" anim="Pico Down Note MISS" name="singDOWNmiss"/>
	<anim x="24" loop="false" y="66" fps="24" anim="pico Up note miss" name="singUPmiss"/>
	<anim x="82" loop="false" y="27" fps="24" anim="Pico NOTE LEFT miss" name="singRIGHTmiss"/>
	<anim x="405" loop="false" y="49" fps="24" anim="Shot" name="shot"/>
</character>
